Workbook

Sheet Raw Data
A1: VEDA TECHNOLOGY | TASK 5: RAW DATA
A2: Sample Superstore-style practice dataset (synthetically generated for this workbook). Original data tab: keep unchanged.
A4: Order ID | B4: Order Date | C4: Region | D4: State | E4: Segment | F4: Category | G4: Sub-Category | H4: Sales | I4: Quantity | J4: Profit
A5: ORD-00001 | B5: 45670 | C5: West | D5: Washington | E5: Home Office | F5: Technology | G5: Accessories | H5: 45.72 | I5: 5 | J5: -2.63
A6: ORD-00002 | B6: 45960 | C6: West | D6: California | E6: Consumer | F6: Furniture | G6: Chairs | H6: 28.4 | I6: 7 | J6: -4.66
A7: ORD-00003 | B7: 45945 | C7: West | D7: Nevada | E7: Consumer | F7: Furniture | G7: Tables | H7: 51.2 | I7: 4 | J7: 9.11
A8: ORD-00004 | B8: 45661 | C8: Central | D8: Colorado | E8: Corporate | F8: Office Supplies | G8: Envelopes | H8: 98.72 | I8: 3 | J8: 16.69
A9: ORD-00005 | B9: 45830 | C9: East | D9: New York | E9: Corporate | F9: Furniture | G9: Furnishings | H9: 26.43 | I9: 2 | J9: -3.53
A10: ORD-00006 | B10: 45967 | C10: Central | D10: Michigan | E10: Home Office | F10: Technology | G10: Phones | H10: 26.43 | I10: 5 | J10: 5.91
A11: ORD-00007 | B11: 45698 | C11: South | D11: Virginia | E11: Home Office | F11: Furniture | G11: Chairs | H11: 102.97 | I11: 5 | J11: 24.17
A12: ORD-00008 | B12: 45681 | C12: West | D12: California | E12: Consumer | F12: Furniture | G12: Tables | H12: 56.01 | I12: 4 | J12: 11.57
A13: ORD-00009 | B13: 45852 | C13: West | D13: Oregon | E13: Consumer | F13: Technology | G13: Phones | H13: 22.15 | I13: 5 | J13: 1.03
A14: ORD-00010 | B14: 45765 | C14: Central | D14: Texas | E14: Home Office | F14: Office Supplies | G14: Art | H14: 47.32 | I14: 5 | J14: 8.09
A15: ORD-00011 | B15: 45931 | C15: East | D15: Massachusetts | E15: Corporate | F15: Technology | G15: Accessories | H15: 22.25 | I15: 4 | J15: -2.19
A16: ORD-00012 | B16: 46008 | C16: East | D16: New York | E16: Consumer | F16: Technology | G16: Accessories | H16: 22.21 | I16: 6 | J16: 5.36
... A504: ORD-00500 | B504: 45990 | C504: South | D504: Virginia | E504: Consumer | F504: Office Supplies | G504: Binders | H504: 11.17 | I504: 6 | J504: -1.04

Sheet Working
A1: VEDA TECHNOLOGY | WORKING & FORMULAS
A2: Formula-based analysis: the raw-data tab is kept separate. Fill formulas down to extend the analysis.
A4: Order ID | B4: Order Date | C4: Region | D4: State | E4: Segment | F4: Category | G4: Sub-Category | H4: Sales | I4: Quantity | J4: Profit | K4: Month | L4: Profit Margin
A5: ='Raw Data'!A5 | B5: ='Raw Data'!B5 | C5: ='Raw Data'!C5 | D5: ='Raw Data'!D5 | E5: ='Raw Data'!E5 | F5: ='Raw Data'!F5 | G5: ='Raw Data'!G5 | H5: ='Raw Data'!H5 | ... J5: ='Raw Data'!J5 | K5: =TEXT(B5,"mmm yyyy") | L5: =IFERROR(J5/H5,0)
A6: ='Raw Data'!A6 | B6: ='Raw Data'!B6 | C6: ='Raw Data'!C6 | D6: ='Raw Data'!D6 | E6: ='Raw Data'!E6 | F6: ='Raw Data'!F6 | G6: ='Raw Data'!G6 | H6: ='Raw Data'!H6 | ... J6: ='Raw Data'!J6 | K6: =TEXT(B6,"mmm yyyy") | L6: =IFERROR(J6/H6,0)
A7: ='Raw Data'!A7 | B7: ='Raw Data'!B7 | C7: ='Raw Data'!C7 | D7: ='Raw Data'!D7 | E7: ='Raw Data'!E7 | F7: ='Raw Data'!F7 | G7: ='Raw Data'!G7 | H7: ='Raw Data'!H7 | ... J7: ='Raw Data'!J7 | K7: =TEXT(B7,"mmm yyyy") | L7: =IFERROR(J7/H7,0)
A8: ='Raw Data'!A8 | B8: ='Raw Data'!B8 | C8: ='Raw Data'!C8 | D8: ='Raw Data'!D8 | E8: ='Raw Data'!E8 | F8: ='Raw Data'!F8 | G8: ='Raw Data'!G8 | H8: ='Raw Data'!H8 | ... J8: ='Raw Data'!J8 | K8: =TEXT(B8,"mmm yyyy") | L8: =IFERROR(J8/H8,0)
A9: ='Raw Data'!A9 | B9: ='Raw Data'!B9 | C9: ='Raw Data'!C9 | D9: ='Raw Data'!D9 | E9: ='Raw Data'!E9 | F9: ='Raw Data'!F9 | G9: ='Raw Data'!G9 | H9: ='Raw Data'!H9 | ... J9: ='Raw Data'!J9 | K9: =TEXT(B9,"mmm yyyy") | L9: =IFERROR(J9/H9,0)
A10: ='Raw Data'!A10 | B10: ='Raw Data'!B10 | C10: ='Raw Data'!C10 | D10: ='Raw Data'!D10 | E10: ='Raw Data'!E10 | F10: ='Raw Data'!F10 | G10: ='Raw Data'!G10 | H10: ='Raw Data'!H10 | ... J10: ='Raw Data'!J10 | K10: =TEXT(B10,"mmm yyyy") | L10: =IFERROR(J10/H10,0)
A11: ='Raw Data'!A11 | B11: ='Raw Data'!B11 | C11: ='Raw Data'!C11 | D11: ='Raw Data'!D11 | E11: ='Raw Data'!E11 | F11: ='Raw Data'!F11 | G11: ='Raw Data'!G11 | H11: ='Raw Data'!H11 | ... J11: ='Raw Data'!J11 | K11: =TEXT(B11,"mmm yyyy") | L11: =IFERROR(J11/H11,0)
A12: ='Raw Data'!A12 | B12: ='Raw Data'!B12 | C12: ='Raw Data'!C12 | D12: ='Raw Data'!D12 | E12: ='Raw Data'!E12 | F12: ='Raw Data'!F12 | G12: ='Raw Data'!G12 | H12: ='Raw Data'!H12 | ... J12: ='Raw Data'!J12 | K12: =TEXT(B12,"mmm yyyy") | L12: =IFERROR(J12/H12,0)
A13: ='Raw Data'!A13 | B13: ='Raw Data'!B13 | C13: ='Raw Data'!C13 | D13: ='Raw Data'!D13 | E13: ='Raw Data'!E13 | F13: ='Raw Data'!F13 | G13: ='Raw Data'!G13 | H13: ='Raw Data'!H13 | ... J13: ='Raw Data'!J13 | K13: =TEXT(B13,"mmm yyyy") | L13: =IFERROR(J13/H13,0)
A14: ='Raw Data'!A14 | B14: ='Raw Data'!B14 | C14: ='Raw Data'!C14 | D14: ='Raw Data'!D14 | E14: ='Raw Data'!E14 | F14: ='Raw Data'!F14 | G14: ='Raw Data'!G14 | H14: ='Raw Data'!H14 | ... J14: ='Raw Data'!J14 | K14: =TEXT(B14,"mmm yyyy") | L14: =IFERROR(J14/H14,0)
A15: ='Raw Data'!A15 | B15: ='Raw Data'!B15 | C15: ='Raw Data'!C15 | D15: ='Raw Data'!D15 | E15: ='Raw Data'!E15 | F15: ='Raw Data'!F15 | G15: ='Raw Data'!G15 | H15: ='Raw Data'!H15 | ... J15: ='Raw Data'!J15 | K15: =TEXT(B15,"mmm yyyy") | L15: =IFERROR(J15/H15,0)
A16: ='Raw Data'!A16 | B16: ='Raw Data'!B16 | C16: ='Raw Data'!C16 | D16: ='Raw Data'!D16 | E16: ='Raw Data'!E16 | F16: ='Raw Data'!F16 | G16: ='Raw Data'!G16 | H16: ='Raw Data'!H16 | ... J16: ='Raw Data'!J16 | K16: =TEXT(B16,"mmm yyyy") | L16: =IFERROR(J16/H16,0)
... A504: ='Raw Data'!A504 | B504: ='Raw Data'!B504 | C504: ='Raw Data'!C504 | D504: ='Raw Data'!D504 | E504: ='Raw Data'!E504 | F504: ='Raw Data'!F504 | G504: ='Raw Data'!G504 | H504: ='Raw Data'!H504 | ... J504: ='Raw Data'!J504 | K504: =TEXT(B504,"mmm yyyy") | L504: =IFERROR(J504/H504,0)

Sheet Summary
A1: VEDA TECHNOLOGY | EXCEL DATA ANALYSIS SUMMARY
A2: KPIs and five formula-driven PivotTable-style summaries. Refresh/recalculate in Excel after opening.
A4: KEY PERFORMANCE INDICATORS
A5: Total Sales | D5: Total Profit | G5: Total Quantity | J5: Average Profit Margin
A6: =SUM(Working!H5:H504) | D6: =SUM(Working!J5:J504) | G6: =SUM(Working!I5:I504) | J6: =IFERROR(SUM(Working!J5:J504)/SUM(Working!H5:H504),0)
A9: PIVOT-STYLE 1 | SALES BY CATEGORY | D9: PIVOT-STYLE 2 | SALES BY REGION | G9: PIVOT-STYLE 3 | PROFIT BY CATEGORY
A10: Category | B10: Total Sales | D10: Region | E10: Total Sales | G10: Category | H10: Total Profit
A11: Furniture | B11: =SUMIFS(Working!$H$5:$H$504,Working!$F$5:$F$504,A11) | D11: Central | E11: =SUMIFS(Working!$H$5:$H$504,Working!$C$5:$C$504,D11) | G11: Furniture | H11: =SUMIFS(Working!$J$5:$J$504,Working!$F$5:$F$504,G11)
A12: Office Supplies | B12: =SUMIFS(Working!$H$5:$H$504,Working!$F$5:$F$504,A12) | D12: East | E12: =SUMIFS(Working!$H$5:$H$504,Working!$C$5:$C$504,D12) | G12: Office Supplies | H12: =SUMIFS(Working!$J$5:$J$504,Working!$F$5:$F$504,G12)
A13: Technology | B13: =SUMIFS(Working!$H$5:$H$504,Working!$F$5:$F$504,A13) | D13: South | E13: =SUMIFS(Working!$H$5:$H$504,Working!$C$5:$C$504,D13) | G13: Technology | H13: =SUMIFS(Working!$J$5:$J$504,Working!$F$5:$F$504,G13)
D14: West | E14: =SUMIFS(Working!$H$5:$H$504,Working!$C$5:$C$504,D14)
A17: PIVOT-STYLE 4 | SALES BY SEGMENT | D17: PIVOT-STYLE 5 | MONTHLY SALES TREND
A18: Segment | B18: Total Sales | D18: Month | E18: Total Sales
A19: Consumer | B19: =SUMIFS(Working!$H$5:$H$504,Working!$E$5:$E$504,A19) | D19: Jan 2025 | E19: =SUMIFS(Working!$H$5:$H$504,Working!$K$5:$K$504,D19)
A20: Corporate | B20: =SUMIFS(Working!$H$5:$H$504,Working!$E$5:$E$504,A20) | D20: Feb 2025 | E20: =SUMIFS(Working!$H$5:$H$504,Working!$K$5:$K$504,D20)
A21: Home Office | B21: =SUMIFS(Working!$H$5:$H$504,Working!$E$5:$E$504,A21) | D21: Mar 2025 | E21: =SUMIFS(Working!$H$5:$H$504,Working!$K$5:$K$504,D21)
D22: Apr 2025 | E22: =SUMIFS(Working!$H$5:$H$504,Working!$K$5:$K$504,D22)
D23: May 2025 | E23: =SUMIFS(Working!$H$5:$H$504,Working!$K$5:$K$504,D23)
D24: Jun 2025 | E24: =SUMIFS(Working!$H$5:$H$504,Working!$K$5:$K$504,D24)
D25: Jul 2025 | E25: =SUMIFS(Working!$H$5:$H$504,Working!$K$5:$K$504,D25)
D26: Aug 2025 | E26: =SUMIFS(Working!$H$5:$H$504,Working!$K$5:$K$504,D26)
D27: Sep 2025 | E27: =SUMIFS(Working!$H$5:$H$504,Working!$K$5:$K$504,D27)
D28: Oct 2025 | E28: =SUMIFS(Working!$H$5:$H$504,Working!$K$5:$K$504,D28)
D29: Nov 2025 | E29: =SUMIFS(Working!$H$5:$H$504,Working!$K$5:$K$504,D29)
D30: Dec 2025 | E30: =SUMIFS(Working!$H$5:$H$504,Working!$K$5:$K$504,D30)
A33: KEY FINDINGS (based on this workbook's sample data)
A34: The analysis of 500 sample retail order lines shows total sales of $21,079.89 and total profit of $1,297.57. Office Supplies is the highest-sales category, while South is the highest-sales region. May 2025 is the strongest month by sales in this sample. These summaries demonstrate how formulas can compare category, regional, segment, profit, and monthly performance. Note: this workbook uses synthetically generated Superstore-style practice data, not the official Sample Superstore dataset; results are for Excel practice only.

Sheet Read Me
A1: TASK 5 | HOW TO USE THIS WORKBOOK
A2: Prepared for Veda Technology Data Analytics Track — Level 1 Day 5.
A4: Workbook contents | B4: Raw Data contains 500 sample order lines; Working links to the raw data and adds Month and Profit Margin formulas; Summary includes KPIs, five formula-driven summary tables and charts.
A5: Important note | B5: The dataset is synthetic Superstore-style practice data. It is not the official Sample Superstore dataset. If your internship requires a specific provided dataset, replace Raw Data with that dataset and adjust formulas/ranges.
A6: Formula practice | B6: Try SUMIFS to calculate sales for one category/region, COUNTIFS to count matching records, and AVERAGEIFS to calculate average sales for a selected category.
A7: Sorting and filtering | B7: Use the filter arrows in Raw Data or Working to filter by region/category and sort Sales from largest to smallest.
A8: Freeze headers | B8: The Raw Data and Working sheets already freeze the header row.
A9: PivotTables | B9: Summary contains five PivotTable-style summaries built with SUMIFS formulas, not native Excel PivotTable objects. If your supervisor specifically requires native PivotTables, create them using Insert > PivotTable from the RawSalesData table.
A10: Interview: SUMIFS vs PivotTable | B10: SUMIFS is useful when you want a fixed result inside a report or formula. PivotTables are faster for exploring many categories and rearranging fields interactively.
A11: Interview: keep source live | B11: Format source data as an Excel Table, then create the PivotTable from that table. New rows added to the table can be included after refreshing the PivotTable.
A12: Interview: retail KPI | B12: Sales, profit, profit margin, and order count are useful retail KPIs. Sales shows revenue; profit and margin show whether sales are profitable.
